polypy/__init__.py
polypy/api_cmd.py
polypy/data_access.py
polypy/example.py
polypy/file_paths.yaml
polypy/toolkit.py
polypy/exceptions/__init__.py
polypy/exceptions/exceptions.py
polypy/program_files/request_parameters.yaml
polypy/program_files/settings.yaml
kunkel_polypy-0.2.2.dist-info/LICENSE
kunkel_polypy-0.2.2.dist-info/METADATA
kunkel_polypy-0.2.2.dist-info/WHEEL
kunkel_polypy-0.2.2.dist-info/top_level.txt
kunkel_polypy-0.2.2.dist-info/RECORD
