Metadata-Version: 2.1
Name: kunkel-polypy
Version: 0.2.2
Summary: A small python library for interfacing with, gathering and exporting data from the polygon.io API
Author-email: Branden Kunkel <kunkel.branden6130@gmail.com>
Project-URL: Homepage, https://github.com/Branden-Kunkel/polypy
Classifier: Programming Language :: Python :: 3
Classifier: Operating System :: OS Independent
Classifier: Development Status :: 3 - Alpha
Classifier: Environment :: Console
Classifier: License :: OSI Approved :: GNU General Public License v3 (GPLv3)
Requires-Python: >=3.10
License-File: LICENSE
Requires-Dist: requests ==2.31.0
Requires-Dist: PyYAML ==6.0.1
